auditmatica/__init__.py
auditmatica/access_log.py
auditmatica/cef.py
auditmatica/events.py
cli/__init__.py
cli/cli.py
cli/syslog.py
tests/__init__.py
tests/test_access_log_parser.py
tests/test_cef.py
tests/test_cli.py
auditmatica-0.1.0.dist-info/LICENSE
auditmatica-0.1.0.dist-info/METADATA
auditmatica-0.1.0.dist-info/WHEEL
auditmatica-0.1.0.dist-info/entry_points.txt
auditmatica-0.1.0.dist-info/top_level.txt
auditmatica-0.1.0.dist-info/RECORD
