Metadata-Version: 2.1
Name: auditmatica
Version: 0.1.0
Summary: Audit Archivematica user activities via nginx access logs.
Home-page: https://github.com/artefactual-labs/auditmatica
Author: Artefactual Systems, Inc.
Author-email: info@artefactual.com
License: AGPL 3
Platform: UNKNOWN
Classifier: Programming Language :: Python :: 3
Classifier: License :: OSI Approved :: GNU Affero General Public License v3
Classifier: Operating System :: OS Independent
Requires-Python: >=3.6
Requires-Dist: Click
